{"id": "black.mode", "path": "src\\black\\mode.py", "mtime": 1666396179, "size": 6904, "hash": "0a22752ced4844ccbe802b40775536d2db9f62372c45f9233fad5f23b802820f", "data_mtime": 1666307365, "dependencies": ["sys", "dataclasses", "enum", "hashlib", "operator", "typing", "warnings", "typing_extensions", "black.const", "builtins", "_operator", "_typeshed", "_warnings", "abc", "array", "ctypes", "mmap"], "suppressed": [], "options": {"disallow_any_generics": true, "show_none_errors": true, "strict_optional": true, "warn_no_return": true, "disallow_any_decorated": false, "allow_untyped_globals": false, "disallow_any_expr": false, "implicit_reexport": true, "disallow_any_explicit": false, "disallow_subclassing_any": true, "disallow_untyped_defs": true, "bazel": false, "always_false": [], "disallow_incomplete_defs": true, "follow_imports": "normal", "ignore_missing_imports": true, "platform": "win32", "local_partial_types": false, "disallow_any_unimported": false, "disallow_untyped_decorators": true, "warn_return_any": true, "plugins": [], "allow_redefinition": false, "strict_equality": true, "strict_optional_whitelist": null, "warn_unused_ignores": true, "mypyc": false, "follow_imports_for_stubs": false, "ignore_errors": false, "no_implicit_optional": true, "disallow_untyped_calls": true, "always_true": [], "strict_concatenate": true, "check_untyped_defs": true, "warn_unreachable": true}, "dep_prios": [10, 5, 5, 5, 5, 5, 5, 5, 5, 5, 30, 30, 30, 30, 30, 30, 30], "dep_lines": [7, 8, 9, 10, 11, 12, 13, 16, 20, 1, 1, 1, 1, 1, 1, 1, 1], "interface_hash": "756c9cdc1d65b29b3e3e0e5b93cb94e3f793f8d7e9e3dad2bd3eeaa6e44ac13c", "version_id": "0.971", "ignore_all": false, "plugin_data": null}