{".class": "MypyFile", "_fullname": "blib2to3.pgen2.driver", "future_import_flags": [], "is_partial_stub_package": false, "is_stub": false, "names": {".class": "SymbolTable", "Any": {".class": "SymbolTableNode", "cross_ref": "typing.Any", "kind": "Gdef", "module_public": false}, "Driver": {".class": "SymbolTableNode", "kind": "Gdef", "node": {".class": "TypeInfo", "_promote": [], "abstract_attributes": [], "bases": ["builtins.object"], "declared_metaclass": null, "defn": {".class": "ClassDef", "fullname": "blib2to3.pgen2.driver.Driver", "name": "Driver", "type_vars": []}, "deletable_attributes": [], "flags": [], "fullname": "blib2to3.pgen2.driver.Driver", "has_param_spec_type": false, "metaclass_type": null, "metadata": {}, "module_name": "blib2to3.pgen2.driver", "mro": ["blib2to3.pgen2.driver.Driver", "builtins.object"], "names": {".class": "SymbolTable", "__init__": {".class": "SymbolTableNode", "kind": "Mdef", "node": {".class": "FuncDef", "arg_kinds": [0, 0, 1], "arg_names": ["self", "grammar", "logger"], "flags": [], "fullname": "blib2to3.pgen2.driver.Driver.__init__", "name": "__init__", "type": {".class": "CallableType", "arg_kinds": [0, 0, 1], "arg_names": ["self", "grammar", "logger"], "arg_types": ["blib2to3.pgen2.driver.Driver", "blib2to3.pgen2.grammar.Grammar", {".class": "UnionType", "items": ["logging.Logger", {".class": "NoneType"}]}], "bound_args": [], "def_extras": {"first_arg": "self"}, "fallback": "builtins.function", "from_concatenate": false, "implicit": false, "is_ellipsis_args": false, "name": "__init__ of Driver", "ret_type": {".class": "NoneType"}, "type_guard": null, "variables": []}}}, "_partially_consume_prefix": {".class": "SymbolTableNode", "kind": "Mdef", "node": {".class": "FuncDef", "arg_kinds": [0, 0, 0], "arg_names": ["self", "prefix", "column"], "flags": [], "fullname": "blib2to3.pgen2.driver.Driver._partially_consume_prefix", "name": "_partially_consume_prefix", "type": {".class": "CallableType", "arg_kinds": [0, 0, 0], "arg_names": ["self", "prefix", "column"], "arg_types": ["blib2to3.pgen2.driver.Driver", "builtins.str", "builtins.int"], "bound_args": [], "def_extras": {"first_arg": "self"}, "fallback": "builtins.function", "from_concatenate": false, "implicit": false, "is_ellipsis_args": false, "name": "_partially_consume_prefix of Driver", "ret_type": {".class": "TupleType", "implicit": false, "items": ["builtins.str", "builtins.str"], "partial_fallback": {".class": "Instance", "args": [{".class": "AnyType", "missing_import_name": null, "source_any": null, "type_of_any": 6}], "type_ref": "builtins.tuple"}}, "type_guard": null, "variables": []}}}, "grammar": {".class": "SymbolTableNode", "implicit": true, "kind": "Mdef", "node": {".class": "Var", "flags": [], "fullname": "blib2to3.pgen2.driver.Driver.grammar", "name": "grammar", "type": "blib2to3.pgen2.grammar.Grammar"}}, "logger": {".class": "SymbolTableNode", "implicit": true, "kind": "Mdef", "node": {".class": "Var", "flags": [], "fullname": "blib2to3.pgen2.driver.Driver.logger", "name": "logger", "type": "logging.Logger"}}, "parse_file": {".class": "SymbolTableNode", "kind": "Mdef", "node": {".class": "FuncDef", "arg_kinds": [0, 0, 1, 1], "arg_names": ["self", "filename", "encoding", "debug"], "flags": [], "fullname": "blib2to3.pgen2.driver.Driver.parse_file", "name": "parse_file", "type": {".class": "CallableType", "arg_kinds": [0, 0, 1, 1], "arg_names": ["self", "filename", "encoding", "debug"], "arg_types": ["blib2to3.pgen2.driver.Driver", {".class": "TypeAliasType", "args": [], "type_ref": "blib2to3.pgen2.driver.Path"}, {".class": "UnionType", "items": ["builtins.str", {".class": "NoneType"}]}, "builtins.bool"], "bound_args": [], "def_extras": {"first_arg": "self"}, "fallback": "builtins.function", "from_concatenate": false, "implicit": false, "is_ellipsis_args": false, "name": "parse_file of Driver", "ret_type": {".class": "TypeAliasType", "args": [], "type_ref": "blib2to3.pytree.NL"}, "type_guard": null, "variables": []}}}, "parse_stream": {".class": "SymbolTableNode", "kind": "Mdef", "node": {".class": "FuncDef", "arg_kinds": [0, 0, 1], "arg_names": ["self", "stream", "debug"], "flags": [], "fullname": "blib2to3.pgen2.driver.Driver.parse_stream", "name": "parse_stream", "type": {".class": "CallableType", "arg_kinds": [0, 0, 1], "arg_names": ["self", "stream", "debug"], "arg_types": ["blib2to3.pgen2.driver.Driver", {".class": "Instance", "args": ["builtins.str"], "type_ref": "typing.IO"}, "builtins.bool"], "bound_args": [], "def_extras": {"first_arg": "self"}, "fallback": "builtins.function", "from_concatenate": false, "implicit": false, "is_ellipsis_args": false, "name": "parse_stream of Driver", "ret_type": {".class": "TypeAliasType", "args": [], "type_ref": "blib2to3.pytree.NL"}, "type_guard": null, "variables": []}}}, "parse_stream_raw": {".class": "SymbolTableNode", "kind": "Mdef", "node": {".class": "FuncDef", "arg_kinds": [0, 0, 1], "arg_names": ["self", "stream", "debug"], "flags": [], "fullname": "blib2to3.pgen2.driver.Driver.parse_stream_raw", "name": "parse_stream_raw", "type": {".class": "CallableType", "arg_kinds": [0, 0, 1], "arg_names": ["self", "stream", "debug"], "arg_types": ["blib2to3.pgen2.driver.Driver", {".class": "Instance", "args": ["builtins.str"], "type_ref": "typing.IO"}, "builtins.bool"], "bound_args": [], "def_extras": {"first_arg": "self"}, "fallback": "builtins.function", "from_concatenate": false, "implicit": false, "is_ellipsis_args": false, "name": "parse_stream_raw of Driver", "ret_type": {".class": "TypeAliasType", "args": [], "type_ref": "blib2to3.pytree.NL"}, "type_guard": null, "variables": []}}}, "parse_string": {".class": "SymbolTableNode", "kind": "Mdef", "node": {".class": "FuncDef", "arg_kinds": [0, 0, 1], "arg_names": ["self", "text", "debug"], "flags": [], "fullname": "blib2to3.pgen2.driver.Driver.parse_string", "name": "parse_string", "type": {".class": "CallableType", "arg_kinds": [0, 0, 1], "arg_names": ["self", "text", "debug"], "arg_types": ["blib2to3.pgen2.driver.Driver", "builtins.str", "builtins.bool"], "bound_args": [], "def_extras": {"first_arg": "self"}, "fallback": "builtins.function", "from_concatenate": false, "implicit": false, "is_ellipsis_args": false, "name": "parse_string of Driver", "ret_type": {".class": "TypeAliasType", "args": [], "type_ref": "blib2to3.pytree.NL"}, "type_guard": null, "variables": []}}}, "parse_tokens": {".class": "SymbolTableNode", "kind": "Mdef", "node": {".class": "FuncDef", "arg_kinds": [0, 0, 1], "arg_names": ["self", "tokens", "debug"], "flags": [], "fullname": "blib2to3.pgen2.driver.Driver.parse_tokens", "name": "parse_tokens", "type": {".class": "CallableType", "arg_kinds": [0, 0, 1], "arg_names": ["self", "tokens", "debug"], "arg_types": ["blib2to3.pgen2.driver.Driver", {".class": "Instance", "args": [{".class": "TypeAliasType", "args": [], "type_ref": "blib2to3.pgen2.tokenize.GoodTokenInfo"}], "type_ref": "typing.Iterable"}, "builtins.bool"], "bound_args": [], "def_extras": {"first_arg": "self"}, "fallback": "builtins.function", "from_concatenate": false, "implicit": false, "is_ellipsis_args": false, "name": "parse_tokens of Driver", "ret_type": {".class": "TypeAliasType", "args": [], "type_ref": "blib2to3.pytree.NL"}, "type_guard": null, "variables": []}}}}, "slots": null, "tuple_type": null, "type_vars": [], "typeddict_type": null}}, "Generic": {".class": "SymbolTableNode", "cross_ref": "typing.Generic", "kind": "Gdef", "module_public": false}, "GoodTokenInfo": {".class": "SymbolTableNode", "cross_ref": "blib2to3.pgen2.tokenize.GoodTokenInfo", "kind": "Gdef", "module_public": false}, "Grammar": {".class": "SymbolTableNode", "cross_ref": "blib2to3.pgen2.grammar.Grammar", "kind": "Gdef", "module_public": false}, "IO": {".class": "SymbolTableNode", "cross_ref": "typing.IO", "kind": "Gdef", "module_public": false}, "Iterable": {".class": "SymbolTableNode", "cross_ref": "typing.Iterable", "kind": "Gdef", "module_public": false}, "Iterator": {".class": "SymbolTableNode", "cross_ref": "typing.Iterator", "kind": "Gdef", "module_public": false}, "List": {".class": "SymbolTableNode", "cross_ref": "typing.List", "kind": "Gdef", "module_public": false}, "Logger": {".class": "SymbolTableNode", "cross_ref": "logging.Logger", "kind": "Gdef", "module_public": false}, "NL": {".class": "SymbolTableNode", "cross_ref": "blib2to3.pytree.NL", "kind": "Gdef", "module_public": false}, "Optional": {".class": "SymbolTableNode", "cross_ref": "typing.Optional", "kind": "Gdef", "module_public": false}, "Path": {".class": "SymbolTableNode", "kind": "Gdef", "module_public": false, "node": {".class": "TypeAlias", "alias_tvars": [], "column": 0, "fullname": "blib2to3.pgen2.driver.Path", "line": 48, "no_args": false, "normalized": false, "target": {".class": "UnionType", "items": ["builtins.str", {".class": "Instance", "args": ["builtins.str"], "type_ref": "os.PathLike"}]}}}, "ReleaseRange": {".class": "SymbolTableNode", "kind": "Gdef", "module_public": false, "node": {".class": "TypeInfo", "_promote": [], "abstract_attributes": [], "bases": ["builtins.object"], "declared_metaclass": null, "defn": {".class": "ClassDef", "fullname": "blib2to3.pgen2.driver.ReleaseRange", "name": "ReleaseRange", "type_vars": []}, "deletable_attributes": [], "flags": [], "fullname": "blib2to3.pgen2.driver.ReleaseRange", "has_param_spec_type": false, "metaclass_type": null, "metadata": {"dataclass": {"attributes": [{"column": 4, "has_default": false, "is_in_init": true, "is_init_var": false, "kw_only": false, "line": 53, "name": "start", "type": "builtins.int"}, {"column": 4, "has_default": true, "is_in_init": true, "is_init_var": false, "kw_only": false, "line": 54, "name": "end", "type": {".class": "UnionType", "items": ["builtins.int", {".class": "NoneType"}]}}, {"column": 4, "has_default": true, "is_in_init": true, "is_init_var": false, "kw_only": false, "line": 55, "name": "tokens", "type": {".class": "Instance", "args": [{".class": "AnyType", "missing_import_name": null, "source_any": null, "type_of_any": 2}], "type_ref": "builtins.list"}}], "frozen": false}, "dataclass_tag": {}}, "module_name": "blib2to3.pgen2.driver", "mro": ["blib2to3.pgen2.driver.ReleaseRange", "builtins.object"], "names": {".class": "SymbolTable", "__dataclass_fields__": {".class": "SymbolTableNode", "kind": "Mdef", "node": {".class": "Var", "flags": ["is_ready"], "fullname": "blib2to3.pgen2.driver.ReleaseRange.__dataclass_fields__", "name": "__dataclass_fields__", "type": {".class": "Instance", "args": ["builtins.str", {".class": "Instance", "args": [{".class": "AnyType", "missing_import_name": null, "source_any": null, "type_of_any": 2}], "type_ref": "dataclasses.Field"}], "type_ref": "builtins.dict"}}, "plugin_generated": true}, "__init__": {".class": "SymbolTableNode", "kind": "Mdef", "node": {".class": "FuncDef", "arg_kinds": [0, 0, 1, 1], "arg_names": ["self", "start", "end", "tokens"], "flags": [], "fullname": "blib2to3.pgen2.driver.ReleaseRange.__init__", "name": "__init__", "type": {".class": "CallableType", "arg_kinds": [0, 0, 1, 1], "arg_names": ["self", "start", "end", "tokens"], "arg_types": ["blib2to3.pgen2.driver.ReleaseRange", "builtins.int", {".class": "UnionType", "items": ["builtins.int", {".class": "NoneType"}]}, {".class": "Instance", "args": [{".class": "AnyType", "missing_import_name": null, "source_any": null, "type_of_any": 2}], "type_ref": "builtins.list"}], "bound_args": [], "def_extras": {}, "fallback": "builtins.function", "from_concatenate": false, "implicit": false, "is_ellipsis_args": false, "name": "__init__ of ReleaseRange", "ret_type": {".class": "NoneType"}, "type_guard": null, "variables": []}}, "plugin_generated": true}, "end": {".class": "SymbolTableNode", "kind": "Mdef", "node": {".class": "Var", "flags": ["is_initialized_in_class", "is_ready", "has_explicit_value"], "fullname": "blib2to3.pgen2.driver.ReleaseRange.end", "name": "end", "type": {".class": "UnionType", "items": ["builtins.int", {".class": "NoneType"}]}}}, "lock": {".class": "SymbolTableNode", "kind": "Mdef", "node": {".class": "FuncDef", "arg_kinds": [0], "arg_names": ["self"], "flags": [], "fullname": "blib2to3.pgen2.driver.ReleaseRange.lock", "name": "lock", "type": {".class": "CallableType", "arg_kinds": [0], "arg_names": ["self"], "arg_types": ["blib2to3.pgen2.driver.ReleaseRange"], "bound_args": [], "def_extras": {"first_arg": "self"}, "fallback": "builtins.function", "from_concatenate": false, "implicit": false, "is_ellipsis_args": false, "name": "lock of ReleaseRange", "ret_type": {".class": "NoneType"}, "type_guard": null, "variables": []}}}, "start": {".class": "SymbolTableNode", "implicit": true, "kind": "Mdef", "node": {".class": "Var", "flags": ["is_initialized_in_class", "is_ready"], "fullname": "blib2to3.pgen2.driver.ReleaseRange.start", "name": "start", "type": "builtins.int"}}, "tokens": {".class": "SymbolTableNode", "kind": "Mdef", "node": {".class": "Var", "flags": ["is_initialized_in_class", "is_ready", "has_explicit_value"], "fullname": "blib2to3.pgen2.driver.ReleaseRange.tokens", "name": "tokens", "type": {".class": "Instance", "args": [{".class": "AnyType", "missing_import_name": null, "source_any": null, "type_of_any": 2}], "type_ref": "builtins.list"}}}}, "slots": null, "tuple_type": null, "type_vars": [], "typeddict_type": null}}, "Text": {".class": "SymbolTableNode", "cross_ref": "typing.Text", "kind": "Gdef", "module_public": false}, "TokenProxy": {".class": "SymbolTableNode", "kind": "Gdef", "module_public": false, "node": {".class": "TypeInfo", "_promote": [], "abstract_attributes": [], "bases": ["builtins.object"], "declared_metaclass": null, "defn": {".class": "ClassDef", "fullname": "blib2to3.pgen2.driver.TokenProxy", "name": "TokenProxy", "type_vars": []}, "deletable_attributes": [], "flags": [], "fullname": "blib2to3.pgen2.driver.TokenProxy", "has_param_spec_type": false, "metaclass_type": null, "metadata": {}, "module_name": "blib2to3.pgen2.driver", "mro": ["blib2to3.pgen2.driver.TokenProxy", "builtins.object"], "names": {".class": "SymbolTable", "__init__": {".class": "SymbolTableNode", "kind": "Mdef", "node": {".class": "FuncDef", "arg_kinds": [0, 0], "arg_names": ["self", "generator"], "flags": [], "fullname": "blib2to3.pgen2.driver.TokenProxy.__init__", "name": "__init__", "type": {".class": "CallableType", "arg_kinds": [0, 0], "arg_names": ["self", "generator"], "arg_types": ["blib2to3.pgen2.driver.TokenProxy", {".class": "AnyType", "missing_import_name": null, "source_any": null, "type_of_any": 2}], "bound_args": [], "def_extras": {"first_arg": "self"}, "fallback": "builtins.function", "from_concatenate": false, "implicit": false, "is_ellipsis_args": false, "name": "__init__ of TokenProxy", "ret_type": {".class": "NoneType"}, "type_guard": null, "variables": []}}}, "__iter__": {".class": "SymbolTableNode", "kind": "Mdef", "node": {".class": "FuncDef", "arg_kinds": [0], "arg_names": [null], "flags": [], "fullname": "blib2to3.pgen2.driver.TokenProxy.__iter__", "name": "__iter__", "type": {".class": "CallableType", "arg_kinds": [0], "arg_names": [null], "arg_types": ["blib2to3.pgen2.driver.TokenProxy"], "bound_args": [], "def_extras": {"first_arg": "self"}, "fallback": "builtins.function", "from_concatenate": false, "implicit": false, "is_ellipsis_args": false, "name": "__iter__ of TokenProxy", "ret_type": "blib2to3.pgen2.driver.TokenProxy", "type_guard": null, "variables": []}}}, "__next__": {".class": "SymbolTableNode", "kind": "Mdef", "node": {".class": "FuncDef", "arg_kinds": [0], "arg_names": ["self"], "flags": [], "fullname": "blib2to3.pgen2.driver.TokenProxy.__next__", "name": "__next__", "type": {".class": "CallableType", "arg_kinds": [0], "arg_names": ["self"], "arg_types": ["blib2to3.pgen2.driver.TokenProxy"], "bound_args": [], "def_extras": {"first_arg": "self"}, "fallback": "builtins.function", "from_concatenate": false, "implicit": false, "is_ellipsis_args": false, "name": "__next__ of TokenProxy", "ret_type": {".class": "AnyType", "missing_import_name": null, "source_any": null, "type_of_any": 2}, "type_guard": null, "variables": []}}}, "_counter": {".class": "SymbolTableNode", "implicit": true, "kind": "Mdef", "node": {".class": "Var", "flags": [], "fullname": "blib2to3.pgen2.driver.TokenProxy._counter", "name": "_counter", "type": "builtins.int"}}, "_release_ranges": {".class": "SymbolTableNode", "implicit": true, "kind": "Mdef", "node": {".class": "Var", "flags": ["explicit_self_type", "is_ready"], "fullname": "blib2to3.pgen2.driver.TokenProxy._release_ranges", "name": "_release_ranges", "type": {".class": "Instance", "args": ["blib2to3.pgen2.driver.ReleaseRange"], "type_ref": "builtins.list"}}}, "_tokens": {".class": "SymbolTableNode", "implicit": true, "kind": "Mdef", "node": {".class": "Var", "flags": [], "fullname": "blib2to3.pgen2.driver.TokenProxy._tokens", "name": "_tokens", "type": {".class": "AnyType", "missing_import_name": null, "source_any": null, "type_of_any": 2}}}, "can_advance": {".class": "SymbolTableNode", "kind": "Mdef", "node": {".class": "FuncDef", "arg_kinds": [0, 0], "arg_names": ["self", "to"], "flags": [], "fullname": "blib2to3.pgen2.driver.TokenProxy.can_advance", "name": "can_advance", "type": {".class": "CallableType", "arg_kinds": [0, 0], "arg_names": ["self", "to"], "arg_types": ["blib2to3.pgen2.driver.TokenProxy", "builtins.int"], "bound_args": [], "def_extras": {"first_arg": "self"}, "fallback": "builtins.function", "from_concatenate": false, "implicit": false, "is_ellipsis_args": false, "name": "can_advance of TokenProxy", "ret_type": "builtins.bool", "type_guard": null, "variables": []}}}, "eat": {".class": "SymbolTableNode", "kind": "Mdef", "node": {".class": "FuncDef", "arg_kinds": [0, 0], "arg_names": ["self", "point"], "flags": [], "fullname": "blib2to3.pgen2.driver.TokenProxy.eat", "name": "eat", "type": {".class": "CallableType", "arg_kinds": [0, 0], "arg_names": ["self", "point"], "arg_types": ["blib2to3.pgen2.driver.TokenProxy", "builtins.int"], "bound_args": [], "def_extras": {"first_arg": "self"}, "fallback": "builtins.function", "from_concatenate": false, "implicit": false, "is_ellipsis_args": false, "name": "eat of TokenProxy", "ret_type": {".class": "AnyType", "missing_import_name": null, "source_any": null, "type_of_any": 2}, "type_guard": null, "variables": []}}}, "release": {".class": "SymbolTableNode", "kind": "Mdef", "node": {".class": "Decorator", "func": {".class": "FuncDef", "arg_kinds": [0], "arg_names": ["self"], "flags": ["is_generator", "is_decorated"], "fullname": "blib2to3.pgen2.driver.TokenProxy.release", "name": "release", "type": {".class": "CallableType", "arg_kinds": [0], "arg_names": ["self"], "arg_types": ["blib2to3.pgen2.driver.TokenProxy"], "bound_args": [], "def_extras": {"first_arg": "self"}, "fallback": "builtins.function", "from_concatenate": false, "implicit": false, "is_ellipsis_args": false, "name": "release of TokenProxy", "ret_type": {".class": "Instance", "args": ["blib2to3.pgen2.driver.TokenProxy"], "type_ref": "typing.Iterator"}, "type_guard": null, "variables": []}}, "is_overload": false, "var": {".class": "Var", "flags": ["is_initialized_in_class", "is_ready"], "fullname": null, "name": "release", "type": {".class": "CallableType", "arg_kinds": [0], "arg_names": ["self"], "arg_types": ["blib2to3.pgen2.driver.TokenProxy"], "bound_args": [], "def_extras": {}, "fallback": "builtins.function", "from_concatenate": false, "implicit": false, "is_ellipsis_args": false, "name": "release of TokenProxy", "ret_type": {".class": "Instance", "args": ["blib2to3.pgen2.driver.TokenProxy"], "type_ref": "contextlib._GeneratorContextManager"}, "type_guard": null, "variables": []}}}}}, "slots": null, "tuple_type": null, "type_vars": [], "typeddict_type": null}}, "Tuple": {".class": "SymbolTableNode", "cross_ref": "typing.Tuple", "kind": "Gdef", "module_public": false}, "TypeVar": {".class": "SymbolTableNode", "cross_ref": "typing.TypeVar", "kind": "Gdef", "module_public": false}, "Union": {".class": "SymbolTableNode", "cross_ref": "typing.Union", "kind": "Gdef", "module_public": false}, "__all__": {".class": "SymbolTableNode", "kind": "Gdef", "module_public": false, "node": {".class": "Var", "flags": ["has_explicit_value"], "fullname": "blib2to3.pgen2.driver.__all__", "name": "__all__", "type": {".class": "Instance", "args": ["builtins.str"], "type_ref": "builtins.list"}}}, "__annotations__": {".class": "SymbolTableNode", "kind": "Gdef", "module_public": false, "node": {".class": "Var", "flags": ["is_ready"], "fullname": "blib2to3.pgen2.driver.__annotations__", "name": "__annotations__", "type": {".class": "Instance", "args": ["builtins.str", {".class": "AnyType", "missing_import_name": null, "source_any": null, "type_of_any": 6}], "type_ref": "builtins.dict"}}}, "__author__": {".class": "SymbolTableNode", "kind": "Gdef", "module_public": false, "node": {".class": "Var", "flags": ["is_ready", "has_explicit_value"], "fullname": "blib2to3.pgen2.driver.__author__", "name": "__author__", "type": "builtins.str"}}, "__doc__": {".class": "SymbolTableNode", "kind": "Gdef", "module_public": false, "node": {".class": "Var", "flags": ["is_ready"], "fullname": "blib2to3.pgen2.driver.__doc__", "name": "__doc__", "type": "builtins.str"}}, "__file__": {".class": "SymbolTableNode", "kind": "Gdef", "module_public": false, "node": {".class": "Var", "flags": ["is_ready"], "fullname": "blib2to3.pgen2.driver.__file__", "name": "__file__", "type": "builtins.str"}}, "__name__": {".class": "SymbolTableNode", "kind": "Gdef", "module_public": false, "node": {".class": "Var", "flags": ["is_ready"], "fullname": "blib2to3.pgen2.driver.__name__", "name": "__name__", "type": "builtins.str"}}, "__package__": {".class": "SymbolTableNode", "kind": "Gdef", "module_public": false, "node": {".class": "Var", "flags": ["is_ready"], "fullname": "blib2to3.pgen2.driver.__package__", "name": "__package__", "type": "builtins.str"}}, "_generate_pickle_name": {".class": "SymbolTableNode", "kind": "Gdef", "module_public": false, "node": {".class": "FuncDef", "arg_kinds": [0, 1], "arg_names": ["gt", "cache_dir"], "flags": [], "fullname": "blib2to3.pgen2.driver._generate_pickle_name", "name": "_generate_pickle_name", "type": {".class": "CallableType", "arg_kinds": [0, 1], "arg_names": ["gt", "cache_dir"], "arg_types": [{".class": "TypeAliasType", "args": [], "type_ref": "blib2to3.pgen2.driver.Path"}, {".class": "UnionType", "items": ["builtins.str", {".class": "Instance", "args": ["builtins.str"], "type_ref": "os.PathLike"}, {".class": "NoneType"}]}], "bound_args": [], "def_extras": {"first_arg": null}, "fallback": "builtins.function", "from_concatenate": false, "implicit": false, "is_ellipsis_args": false, "name": "_generate_pickle_name", "ret_type": "builtins.str", "type_guard": null, "variables": []}}}, "_newer": {".class": "SymbolTableNode", "kind": "Gdef", "module_public": false, "node": {".class": "FuncDef", "arg_kinds": [0, 0], "arg_names": ["a", "b"], "flags": [], "fullname": "blib2to3.pgen2.driver._newer", "name": "_newer", "type": {".class": "CallableType", "arg_kinds": [0, 0], "arg_names": ["a", "b"], "arg_types": ["builtins.str", "builtins.str"], "bound_args": [], "def_extras": {"first_arg": null}, "fallback": "builtins.function", "from_concatenate": false, "implicit": false, "is_ellipsis_args": false, "name": "_newer", "ret_type": "builtins.bool", "type_guard": null, "variables": []}}}, "cast": {".class": "SymbolTableNode", "cross_ref": "typing.cast", "kind": "Gdef", "module_public": false}, "contextmanager": {".class": "SymbolTableNode", "cross_ref": "contextlib.contextmanager", "kind": "Gdef", "module_public": false}, "dataclass": {".class": "SymbolTableNode", "cross_ref": "dataclasses.dataclass", "kind": "Gdef", "module_public": false}, "field": {".class": "SymbolTableNode", "cross_ref": "dataclasses.field", "kind": "Gdef", "module_public": false}, "grammar": {".class": "SymbolTableNode", "cross_ref": "blib2to3.pgen2.grammar", "kind": "Gdef", "module_public": false}, "io": {".class": "SymbolTableNode", "cross_ref": "io", "kind": "Gdef", "module_public": false}, "load_grammar": {".class": "SymbolTableNode", "kind": "Gdef", "node": {".class": "FuncDef", "arg_kinds": [1, 1, 1, 1, 1], "arg_names": ["gt", "gp", "save", "force", "logger"], "flags": [], "fullname": "blib2to3.pgen2.driver.load_grammar", "name": "load_grammar", "type": {".class": "CallableType", "arg_kinds": [1, 1, 1, 1, 1], "arg_names": ["gt", "gp", "save", "force", "logger"], "arg_types": ["builtins.str", {".class": "UnionType", "items": ["builtins.str", {".class": "NoneType"}]}, "builtins.bool", "builtins.bool", {".class": "UnionType", "items": ["logging.Logger", {".class": "NoneType"}]}], "bound_args": [], "def_extras": {"first_arg": null}, "fallback": "builtins.function", "from_concatenate": false, "implicit": false, "is_ellipsis_args": false, "name": "load_grammar", "ret_type": "blib2to3.pgen2.grammar.Grammar", "type_guard": null, "variables": []}}}, "load_packaged_grammar": {".class": "SymbolTableNode", "kind": "Gdef", "module_public": false, "node": {".class": "FuncDef", "arg_kinds": [0, 0, 1], "arg_names": ["package", "grammar_source", "cache_dir"], "flags": [], "fullname": "blib2to3.pgen2.driver.load_packaged_grammar", "name": "load_packaged_grammar", "type": {".class": "CallableType", "arg_kinds": [0, 0, 1], "arg_names": ["package", "grammar_source", "cache_dir"], "arg_types": ["builtins.str", "builtins.str", {".class": "UnionType", "items": ["builtins.str", {".class": "Instance", "args": ["builtins.str"], "type_ref": "os.PathLike"}, {".class": "NoneType"}]}], "bound_args": [], "def_extras": {"first_arg": null}, "fallback": "builtins.function", "from_concatenate": false, "implicit": false, "is_ellipsis_args": false, "name": "load_packaged_grammar", "ret_type": "blib2to3.pgen2.grammar.Grammar", "type_guard": null, "variables": []}}}, "logging": {".class": "SymbolTableNode", "cross_ref": "logging", "kind": "Gdef", "module_public": false}, "main": {".class": "SymbolTableNode", "kind": "Gdef", "module_public": false, "node": {".class": "FuncDef", "arg_kinds": [2], "arg_names": ["args"], "flags": [], "fullname": "blib2to3.pgen2.driver.main", "name": "main", "type": {".class": "CallableType", "arg_kinds": [2], "arg_names": ["args"], "arg_types": ["builtins.str"], "bound_args": [], "def_extras": {"first_arg": null}, "fallback": "builtins.function", "from_concatenate": false, "implicit": false, "is_ellipsis_args": false, "name": "main", "ret_type": "builtins.bool", "type_guard": null, "variables": []}}}, "os": {".class": "SymbolTableNode", "cross_ref": "os", "kind": "Gdef", "module_public": false}, "parse": {".class": "SymbolTableNode", "cross_ref": "blib2to3.pgen2.parse", "kind": "Gdef", "module_public": false}, "pgen": {".class": "SymbolTableNode", "cross_ref": "blib2to3.pgen2.pgen", "kind": "Gdef", "module_public": false}, "pkgutil": {".class": "SymbolTableNode", "cross_ref": "pkgutil", "kind": "Gdef", "module_public": false}, "sys": {".class": "SymbolTableNode", "cross_ref": "sys", "kind": "Gdef", "module_public": false}, "token": {".class": "SymbolTableNode", "cross_ref": "blib2to3.pgen2.token", "kind": "Gdef", "module_public": false}, "tokenize": {".class": "SymbolTableNode", "cross_ref": "blib2to3.pgen2.tokenize", "kind": "Gdef", "module_public": false}}, "path": "src\\blib2to3\\pgen2\\driver.py"}